moban_slim/__init__.py
moban_slim/_version.py
moban_slim/engine.py
moban_slim-0.0.2.dist-info/METADATA
moban_slim-0.0.2.dist-info/WHEEL
moban_slim-0.0.2.dist-info/top_level.txt
moban_slim-0.0.2.dist-info/RECORD
